tinie/__init__.py
tinie/data/__init__.py
tinie/figures/__init__.py
tinie/main_routines/__init__.py
tinie/main_routines/calculator.py
tinie/main_routines/greenfunction.py
tinie/main_routines/misc.py
tinie/main_routines/selfenergy.py
tinie/main_routines/tests/__init__.py
tinie/main_routines/tests/test_calculator.py
tinie/main_routines/tests/test_greenfunction.py
tinie/main_routines/tests/test_misc.py
tinie/main_routines/tests/test_selfenergy.py
tinie/scripts/__init__.py
tinie/scripts/make_system_files.py
tinie/scripts/tinie.py
tinie/scripts/tinie_dos.py
tinie/scripts/tinie_draw.py
tinie/scripts/tinie_prepare.py
tinie/systems/__init__.py
tinie/systems/central_region/__init__.py
tinie/systems/central_region/center.py
tinie/systems/central_region/custom_center.py
tinie/systems/central_region/itp2d_center.py
tinie/systems/central_region/octopus_center.py
tinie/systems/central_region/tests/__init__.py
tinie/systems/central_region/tests/test_custom_center.py
tinie/systems/central_region/tests/test_itp2d_center.py
tinie/systems/couplings/__init__.py
tinie/systems/couplings/coupling.py
tinie/systems/couplings/custom_coupling.py
tinie/systems/couplings/one_layer_coupling.py
tinie/systems/couplings/overlap_coupling.py
tinie/systems/couplings/tight_binding_coupling.py
tinie/systems/couplings/tests/__init__.py
tinie/systems/couplings/tests/test_custom_coupling.py
tinie/systems/couplings/tests/test_one_layer_coupling.py
tinie/systems/couplings/tests/test_overlap_coupling.py
tinie/systems/couplings/tests/test_tight_binding_coupling.py
tinie/systems/leads/__init__.py
tinie/systems/leads/box_lead.py
tinie/systems/leads/custom_lead.py
tinie/systems/leads/finite_harmonic_lead.py
tinie/systems/leads/lead.py
tinie/systems/leads/tests/__init__.py
tinie/systems/leads/tests/test_box_lead.py
tinie/systems/leads/tests/test_custom_lead.py
tinie/systems/leads/tests/test_finite_harmonic_lead.py
tinie/systems/read_write/__init__.py
tinie/systems/read_write/system.py
tinie-1.0.6.dist-info/LICENSE
tinie-1.0.6.dist-info/METADATA
tinie-1.0.6.dist-info/WHEEL
tinie-1.0.6.dist-info/entry_points.txt
tinie-1.0.6.dist-info/top_level.txt
tinie-1.0.6.dist-info/RECORD
