Metadata-Version: 2.1
Name: tinie
Version: 1.0.6
Summary: A non-interacting equilibrium 2D quantum transport simulation framework
Home-page: https://gitlab.com/compphys-public/tinie
Author: Rostislav Duda, Joonas Keski-Rahkonen, Janne Solanpää
Author-email: rostislav.duda@tuni.fi
License: MIT
Keywords: numerics quantum transport physics
Platform: UNKNOWN
Classifier: License :: OSI Approved :: Boost Software License 1.0 (BSL-1.0)
Classifier: Programming Language :: Python :: 3.6
Classifier: Topic :: Scientific/Engineering :: Physics
Classifier: Development Status :: 5 - Production/Stable
Classifier: Environment :: Console
Classifier: Intended Audience :: Science/Research
Classifier: Operating System :: POSIX
Requires-Python: >=3.6
Requires-Dist: numpy
Requires-Dist: scipy
Requires-Dist: mpi4py
Requires-Dist: progressbar2
Requires-Dist: findiff
Requires-Dist: matplotlib
Requires-Dist: h5py
Requires-Dist: vegas
